CHANGELOG.rst
LICENSE.txt
MANIFEST.in
README.rst
optionals.txt
pyshanb.conf
requirements.txt
setup.py
pyshanb/__init__.py
pyshanb/__main__.py
pyshanb/_werkzeug.py
pyshanb/cmdoption.py
pyshanb/color.py
pyshanb/conf.py
pyshanb/helper.py
pyshanb/iciba.py
pyshanb/main.py
pyshanb/plugin.py
pyshanb/shanbay.py
pyshanb/utils.py
pyshanb.egg-info/PKG-INFO
pyshanb.egg-info/SOURCES.txt
pyshanb.egg-info/dependency_links.txt
pyshanb.egg-info/entry_points.txt
pyshanb.egg-info/not-zip-safe
pyshanb.egg-info/requires.txt
pyshanb.egg-info/top_level.txt
pyshanb/plugins/__init__.py
pyshanb/plugins/youdao.py