Metadata-Version: 1.0
Name: pyshanb
Version: 0.6.1
Summary: PyShanb - 命令行下的扇贝词典
Home-page: https://github.com/mozillazg/PyShanb
Author: mozillazg
Author-email: mozillazg101@gmail.com
License: MIT
Download-URL: https://github.com/mozillazg/PyShanb
Platform: UNKNOWN
Classifier: Development Status :: 5 - Production/Stable
Classifier: Environment :: Console
Classifier: Intended Audience :: Developers
Classifier: Intended Audience :: Education
Classifier: License :: OSI Approved :: MIT License
Classifier: Operating System :: OS Independent
Classifier: Programming Language :: Python
Classifier: Programming Language :: Python :: 2.6
Classifier: Programming Language :: Python :: 2.7
Classifier: Programming Language :: Python :: 2 :: Only
Classifier: Topic :: Terminals
Classifier: Topic :: Text Processing
Classifier: Topic :: Utilities
